{
  "totalProducts": 43,
  "productsClassified": 43,
  "directAuthorityContracts": 27,
  "productsMissingAuthorityContract": [
    "case_dossier_tariff_shock",
    "case_dossier_team_alignment",
    "case_dossier_escalation_denied",
    "retainer_core",
    "retainer_operational",
    "retainer_institutional",
    "gmi_q1_2026",
    "gmi_q2_2026",
    "gmi_q3_2026",
    "operator_essentials_pack",
    "command_pack",
    "governance_suite",
    "inner_circle",
    "diagnostic_report_basic",
    "diagnostic_report_pro",
    "executive_reporting_priority"
  ],
  "publicProductsMissingAuthorityContract": [],
  "routesAudited": 7,
  "routesDemonstratingAuthority": 6,
  "checkoutFailures": [],
  "adminSurfaceFailures": [],
  "reportSurfaceFailures": [],
  "publicClaimFailures": [],
  "staticReferenceExemptions": [
    {
      "productCode": "case_dossier_tariff_shock",
      "explicit": true,
      "reason": "Case Dossier — Tariff Shock is a static/reference product unless evidence-governed logic is visible.",
      "canClaimIntelligence": false,
      "canClaimJudgement": false
    },
    {
      "productCode": "case_dossier_team_alignment",
      "explicit": true,
      "reason": "Case Dossier — Team Alignment is a static/reference product unless evidence-governed logic is visible.",
      "canClaimIntelligence": false,
      "canClaimJudgement": false
    },
    {
      "productCode": "case_dossier_escalation_denied",
      "explicit": true,
      "reason": "Case Dossier — Escalation Denied is a static/reference product unless evidence-governed logic is visible.",
      "canClaimIntelligence": false,
      "canClaimJudgement": false
    },
    {
      "productCode": "gmi_q1_2026",
      "explicit": true,
      "reason": "Global Market Intelligence Report — Q1 2026 is a static/reference product unless evidence-governed logic is visible.",
      "canClaimIntelligence": false,
      "canClaimJudgement": false
    }
  ],
  "internalOnlyExemptions": [
    {
      "productCode": "retainer_core",
      "explicit": true,
      "reason": "Decision Authority Retainer — Core is internal-only or manually governed by design."
    },
    {
      "productCode": "retainer_operational",
      "explicit": true,
      "reason": "Decision Authority Retainer — Operational is internal-only or manually governed by design."
    },
    {
      "productCode": "retainer_institutional",
      "explicit": true,
      "reason": "Decision Authority Retainer — Institutional is internal-only or manually governed by design."
    },
    {
      "productCode": "gmi_q2_2026",
      "explicit": true,
      "reason": "Global Market Intelligence Report — Q2 2026 is a static/reference product unless evidence-governed logic is visible."
    },
    {
      "productCode": "gmi_q3_2026",
      "explicit": true,
      "reason": "Global Market Intelligence Report — Q3 2026 is a static/reference product unless evidence-governed logic is visible."
    },
    {
      "productCode": "enterprise",
      "explicit": true,
      "reason": "Enterprise is internal-only or manually governed by design."
    },
    {
      "productCode": "additional_collaborator",
      "explicit": true,
      "reason": "Additional Collaborator is internal-only or manually governed by design."
    },
    {
      "productCode": "operator_essentials_pack",
      "explicit": true,
      "reason": "Operator Essentials is internal-only or manually governed by design."
    },
    {
      "productCode": "command_pack",
      "explicit": true,
      "reason": "Command Pack is internal-only or manually governed by design."
    },
    {
      "productCode": "governance_suite",
      "explicit": true,
      "reason": "Governance Suite is internal-only or manually governed by design."
    },
    {
      "productCode": "inner_circle",
      "explicit": true,
      "reason": "Inner Circle is internal-only or manually governed by design."
    },
    {
      "productCode": "diagnostic_report_basic",
      "explicit": true,
      "reason": "Diagnostic Report — Basic is a static/reference product unless evidence-governed logic is visible."
    },
    {
      "productCode": "diagnostic_report_pro",
      "explicit": true,
      "reason": "Diagnostic Report — Pro is a static/reference product unless evidence-governed logic is visible."
    },
    {
      "productCode": "executive_reporting_priority",
      "explicit": true,
      "reason": "Executive Reporting — Advanced is a static/reference product unless evidence-governed logic is visible."
    }
  ],
  "localPassesThatCannotImplyEstateReadiness": [
    "category-demonstration-readiness: contains local category_demonstrated; scope-contained by estate integrity lock",
    "category-route-proof: selected-route pattern pass cannot imply estate readiness; scope-contained by estate integrity lock"
  ],
  "readinessScope": "estate_category_demonstrated",
  "gatePassed": true,
  "localPassContainmentPassed": true,
  "blockingReasons": [
    "One or more local passes must be scope-contained and cannot imply estate readiness."
  ],
  "localGateResult": {
    "routeProof": "PASSED_LOCAL_PATTERN_ONLY",
    "categoryReadiness": "PASSED_ESTATE",
    "productAuthorityContract": "CORE_AND_PUBLIC_CONTRACT_COVERAGE_PASSED",
    "checkout": "PASSED",
    "report": "PASSED",
    "admin": "PASSED"
  },
  "estateCoverageResult": "estate_coverage_clean",
  "finalAuthorityPosition": "Estate category demonstration may be claimed."
}
