{
  "generatedAt": "2026-06-13T21:48:11.371Z",
  "gatesAudited": 8,
  "summary": {
    "medium_gate": 4,
    "narrow_gate": 2,
    "failing_gate": 1,
    "misleading_gate": 1
  },
  "rows": [
    {
      "script": "scripts/check-product-authority-contract.mjs",
      "exists": true,
      "claimsToVerify": "ProductAuthorityContract consistency and public/non-exempt coverage.",
      "actuallyVerifies": "Builds/validates contract records; does not prove product engine runtime behavior.",
      "filesScanned": [
        "reports/product-value-evidence-ledger-v2.json"
      ],
      "filesMissed": [],
      "checksRuntimeWiring": true,
      "checksImports": true,
      "checksRenderedOutput": true,
      "checksGeneratedEvidence": true,
      "canPassWhileProductUnsafe": true,
      "classification": "medium_gate",
      "correctionNeeded": "Keep as useful signal, but do not let it imply runtime truth alone."
    },
    {
      "script": "scripts/check-estate-authority-integrity.mjs",
      "exists": true,
      "claimsToVerify": "Estate-level authority readiness from generated coverage reports.",
      "actuallyVerifies": "Reads generated reports and checks aggregate failures; depends on upstream report correctness.",
      "filesScanned": [],
      "filesMissed": [
        "Direct runtime import checks",
        "browser-rendered route capture"
      ],
      "checksRuntimeWiring": true,
      "checksImports": false,
      "checksRenderedOutput": false,
      "checksGeneratedEvidence": true,
      "canPassWhileProductUnsafe": true,
      "classification": "medium_gate",
      "correctionNeeded": "Keep as useful signal, but do not let it imply runtime truth alone."
    },
    {
      "script": "scripts/check-no-mock-authority.mjs",
      "exists": true,
      "claimsToVerify": "No mock/fixture/placeholder authority grants.",
      "actuallyVerifies": "Scans selected paths for suspicious terms; produces many lexical findings but can pass.",
      "filesScanned": [
        "lib/product/product-authority-contract.ts",
        "lib/product/product-authority-gate.ts",
        "lib/product/authority-gate-hierarchy.ts",
        "lib/product/evidence-classification.ts",
        "lib/product/authority-evidence-source-policy.ts",
        "lib/product/authority-critical-paths.ts",
        "lib/validation/data-source-authority.ts",
        "lib/product/live-route-output-capture.ts",
        "scripts/check-product-authority-contract.mjs",
        "scripts/generate-v2-evidence-ledger.mjs",
        "scripts/verify-evidence-ledger-artifacts.mjs",
        "scripts/capture-live-route-product-output.mjs",
        "scripts/capture-category-route-proof.mjs",
        "scripts/check-surface-claim-authority.mjs",
        "scripts/check-effective-authority-surfaces.mjs",
        "scripts/check-universal-claim-authority.mjs",
        "scripts/check-no-mock-authority.mjs",
        "scripts/check-authority-grant-firewall.mjs",
        "scripts/check-authority-safety-gate.mjs",
        "scripts/check-authority-safe-language.mjs",
        "scripts/reconcile-product-authority-truth.mjs",
        "scripts/scan-product-surface-claims.ts",
        "scripts/check-",
        "scripts/test-"
      ],
      "filesMissed": [
        "Runtime data provenance",
        "rendered output inspection",
        "actual database records"
      ],
      "checksRuntimeWiring": true,
      "checksImports": false,
      "checksRenderedOutput": true,
      "checksGeneratedEvidence": true,
      "canPassWhileProductUnsafe": true,
      "classification": "narrow_gate",
      "correctionNeeded": "Broaden file coverage and add runtime/rendered-output checks."
    },
    {
      "script": "scripts/check-surface-claim-authority.mjs",
      "exists": true,
      "claimsToVerify": "Public claim language does not exceed authority.",
      "actuallyVerifies": "Scans registered surfaces/claims; does not exhaustively scan all public copy.",
      "filesScanned": [],
      "filesMissed": [
        "MDX content",
        "product catalogue copy",
        "comments and report copy outside registered surfaces"
      ],
      "checksRuntimeWiring": false,
      "checksImports": false,
      "checksRenderedOutput": false,
      "checksGeneratedEvidence": true,
      "canPassWhileProductUnsafe": true,
      "classification": "narrow_gate",
      "correctionNeeded": "Broaden file coverage and add runtime/rendered-output checks."
    },
    {
      "script": "scripts/audit-market-adoption-posture.mjs",
      "exists": true,
      "claimsToVerify": "Market adoption posture and pain clarity.",
      "actuallyVerifies": "Static script/content inspection.",
      "filesScanned": [
        "lib/product",
        "lib/commercial",
        "pages/diagnostics/fast.tsx",
        "pages/foundry/decision-test.tsx",
        "components/kernel/FreeSignalResult.tsx",
        "pages/diagnostics/team-assessment.tsx",
        "pages/api/diagnostics/team-alignment.ts",
        "components/diagnostics/AssessmentResultSurface.tsx",
        "pages/diagnostics/enterprise-assessment.tsx",
        "pages/api/diagnostics/enterprise.ts",
        "pages/test-your-decision.tsx",
        "pages/checkout/personal-decision-audit.tsx",
        "pages/decision-instruments/[slug].tsx",
        "pages/decision-centre.tsx",
        "pages/decision-centre/case/[caseId].tsx",
        "lib/product/decision-centre-contract.ts",
        "app/boardroom/dossier/[dossierId]/page.tsx",
        "app/boardroom/dossier/[dossierId]/BoardroomDossierClient.tsx",
        "lib/boardroom/boardroom-dossier-service.ts",
        "pages/intelligence/market.tsx",
        "pages/artifacts/global-market-outlook-q1-2026-public.tsx",
        "lib/intelligence/market-intelligence-lifecycle.ts",
        "pages/admin/authority-center.tsx",
        "pages/admin/index.tsx",
        "components/product/ProductAuthorityPanel.tsx",
        "pages/api/checkout/decision-failure-brief.ts",
        "lib/product/product-fulfilment-contract.ts"
      ],
      "filesMissed": [],
      "checksRuntimeWiring": true,
      "checksImports": true,
      "checksRenderedOutput": true,
      "checksGeneratedEvidence": true,
      "canPassWhileProductUnsafe": false,
      "classification": "medium_gate",
      "correctionNeeded": "Keep as useful signal, but do not let it imply runtime truth alone."
    },
    {
      "script": "scripts/audit-wave-2-product-readiness.mjs",
      "exists": true,
      "claimsToVerify": "Wave 2 product readiness classification.",
      "actuallyVerifies": "Static script/content inspection.",
      "filesScanned": [
        "lib/product/resolve-product-authority.ts",
        "reports/wave-2-product-readiness.json"
      ],
      "filesMissed": [],
      "checksRuntimeWiring": true,
      "checksImports": false,
      "checksRenderedOutput": true,
      "checksGeneratedEvidence": true,
      "canPassWhileProductUnsafe": false,
      "classification": "medium_gate",
      "correctionNeeded": "Keep as useful signal, but do not let it imply runtime truth alone."
    },
    {
      "script": "scripts/check-board-facing-authority-language.mjs",
      "exists": true,
      "claimsToVerify": "Board-facing language does not overstate evidence.",
      "actuallyVerifies": "Scans three files for a small phrase list; currently fails and misses several board-facing surfaces.",
      "filesScanned": [
        "lib/instruments/board-brief-template/engine.ts",
        "lib/constitution/boardroom-mode.ts",
        "lib/boardroom/*.ts",
        "lib/boardroom/*.tsx",
        "pages/boardroom-brief.tsx",
        "pages/boardroom-brief/**",
        "components/admin/reporting/boardroom-mode.tsx",
        "components/diagnostics/results/BoardSnapshot.tsx",
        "components/reporting/boardroom/BoardroomMode.tsx",
        "app/api/executive-reporting/export/boardroom-pdf/route.ts",
        "app/api/admin/boardroom-delivery/**/*.ts",
        "lib/pdf/artifacts/global-market-intelligence-q1-2026-boardroom.tsx",
        "lib/pdf/oversight-brief-pdf.tsx",
        "lib/research/engines/boardroom-dossier-adapter.ts",
        "lib/research/engines/boardroom-mode-adapter.ts",
        "lib/research/engines/executive-report-boardroom-bridge-adapter.ts",
        "lib/intelligence/gmi-board-pack-artifact-service.server.ts",
        "lib/intelligence/gmi-instrument.ts",
        "lib/product/boardroom-archive-contract.ts",
        "lib/product/boardroom-archive-summary.ts",
        "lib/product/boardroom-archive.ts",
        "lib/product/boardroom-dossier-archive.ts",
        "lib/product/boardroom-history-summary.ts",
        "lib/product/product-surface-registry.ts",
        "lib/product/resolve-product-authority.ts",
        "lib/board/evidence-governance.ts",
        "lib/commercial/catalog.ts",
        "lib/commercial/premium-decision-assets.ts",
        "lib/admin/product-surface-registry.ts",
        "lib/admin/reporting/report-pdf.tsx",
        "lib/boardroom/boardroom-delivery-pipeline.ts",
        "lib/boardroom/boardroom-dossier-service.ts",
        "lib/boardroom/dossier-builder.ts",
        "lib/boardroom/dossier-pdf.tsx",
        "lib/boardroom/dossier-types.ts",
        "lib/instruments/governed-instrument-contract.ts",
        "lib/constitution/boardroom-spine-builder.ts"
      ],
      "filesMissed": [
        "components/instruments/BoardBriefBuilderRunner.tsx",
        "app/boardroom/dossier/[dossierId]/BoardroomDossierClient.tsx",
        "app/api/admin/boardroom-delivery/generate/route.ts",
        "lib/product/product-estate-contract.ts",
        "pages/pricing.tsx",
        "pages/products.tsx"
      ],
      "checksRuntimeWiring": true,
      "checksImports": false,
      "checksRenderedOutput": false,
      "checksGeneratedEvidence": true,
      "canPassWhileProductUnsafe": true,
      "classification": "failing_gate",
      "correctionNeeded": "Fix violations and expand scanned surface area before treating as protective."
    },
    {
      "script": "scripts/generate-v2-evidence-ledger.mjs",
      "exists": true,
      "claimsToVerify": "Generate Evidence Ledger v2 authority evidence.",
      "actuallyVerifies": "Generates ledger metadata; generation is not independent validation.",
      "filesScanned": [],
      "filesMissed": [],
      "checksRuntimeWiring": true,
      "checksImports": true,
      "checksRenderedOutput": true,
      "checksGeneratedEvidence": true,
      "canPassWhileProductUnsafe": true,
      "classification": "misleading_gate",
      "correctionNeeded": "Rename or scope as generation only; independent validation must be separate."
    }
  ]
}
